BDHotfixPatchTool/__init__.py
BDHotfixPatchTool/patchTool.py
BDHotfixPatchTool-1.0.1.dist-info/LICENSE
BDHotfixPatchTool-1.0.1.dist-info/METADATA
BDHotfixPatchTool-1.0.1.dist-info/WHEEL
BDHotfixPatchTool-1.0.1.dist-info/entry_points.txt
BDHotfixPatchTool-1.0.1.dist-info/top_level.txt
BDHotfixPatchTool-1.0.1.dist-info/RECORD
