Metadata-Version: 2.1
Name: BDHotfixPatchTool
Version: 1.0.1
Summary: A patch making tool for BDHotfix.
Home-page: https://example.com
Author: zhuyuanqing
Author-email: zhuyuanqing@bytedance.com
License: MIT
Platform: macOS
License-File: LICENSE
Requires-Dist: click (>=7.1.2)
